ipify2/__info__.py
ipify2/__init__.py
ipify2/exceptions.py
ipify2/ipify.py
ipify2/settings.py
ipify2-1.1.0.dist-info/METADATA
ipify2-1.1.0.dist-info/WHEEL
ipify2-1.1.0.dist-info/top_level.txt
ipify2-1.1.0.dist-info/RECORD
