Metadata-Version: 2.1
Name: ipify2
Version: 1.1.0
Summary: Get IP address information via ipify.org
Home-page: https://github.com/nwithan8/ipify2
Author: Nate Harris
Author-email: n8gr8gbln@gmail.com
License: UNLICENSE
Download-URL: https://github.com/nwithan8/ipify2/archive/1.1.0.tar.gz
Keywords: Python,API,client,ipify,ipify2,ip,address,public,ipv4,ipv6,service
Platform: UNKNOWN
Classifier: Development Status :: 5 - Production/Stable
Classifier: Environment :: Console
Classifier: Intended Audience :: Developers
Classifier: License :: Public Domain
Classifier: Operating System :: OS Independent
Classifier: Programming Language :: Python
Classifier: Programming Language :: Python :: 3
Classifier: Programming Language :: Python :: 3.2
Classifier: Programming Language :: Python :: 3.3
Classifier: Programming Language :: Python :: 3.4
Classifier: Programming Language :: Python :: 3.5
Classifier: Programming Language :: Python :: 3.6
Classifier: Programming Language :: Python :: Implementation :: CPython
Classifier: Programming Language :: Python :: Implementation :: PyPy
Classifier: Topic :: Internet
Classifier: Topic :: Software Development
Classifier: Topic :: Software Development :: Libraries
Classifier: Topic :: Software Development :: Libraries :: Python Modules
Classifier: Topic :: Utilities
Requires-Python: >=3.0
Requires-Dist: pytest >=2.7.0
Requires-Dist: pytest-cov >=1.8.1
Requires-Dist: python-coveralls >=2.5.0
Requires-Dist: backoff >=1.0.7
Requires-Dist: requests >=2.7.0
